kupiapi/__init__.py
kupiapi/recipes.py
kupiapi/scraper.py
kupiapi/text_parser.py
kupiapi/kupiapi/__init__.py
kupiapi-1.0.11.dist-info/METADATA
kupiapi-1.0.11.dist-info/WHEEL
kupiapi-1.0.11.dist-info/top_level.txt
kupiapi-1.0.11.dist-info/RECORD
