Metadata-Version: 2.1
Name: kupiapi
Version: 1.0.11
Summary: Scraper API for extracting products data from kupi.cz
Home-page: https://github.com/vorava/kupiapi
Author: Vojtech Orava
Author-email: vojtech.orava@gmail.com
Classifier: Programming Language :: Python :: 3
Classifier: License :: OSI Approved :: MIT License
Classifier: Operating System :: OS Independent
Requires-Dist: beautifulsoup4
Requires-Dist: requests
